fds/__init__.py
fds/sdk/__init__.py
fds/sdk/FactSetNER/__init__.py
fds/sdk/FactSetNER/api_client.py
fds/sdk/FactSetNER/configuration.py
fds/sdk/FactSetNER/exceptions.py
fds/sdk/FactSetNER/model_utils.py
fds/sdk/FactSetNER/rest.py
fds/sdk/FactSetNER/api/__init__.py
fds/sdk/FactSetNER/api/entities_api.py
fds/sdk/FactSetNER/apis/__init__.py
fds/sdk/FactSetNER/model/__init__.py
fds/sdk/FactSetNER/model/associated_organization.py
fds/sdk/FactSetNER/model/entity.py
fds/sdk/FactSetNER/model/input.py
fds/sdk/FactSetNER/model/response.py
fds/sdk/FactSetNER/models/__init__.py
fds.sdk.FactSetNER-0.21.14.dist-info/LICENSE
fds.sdk.FactSetNER-0.21.14.dist-info/METADATA
fds.sdk.FactSetNER-0.21.14.dist-info/WHEEL
fds.sdk.FactSetNER-0.21.14.dist-info/top_level.txt
fds.sdk.FactSetNER-0.21.14.dist-info/RECORD
